{
  "schemaVersion": 1,
  "appId": "com.kengqin.novellibrary.mobile",
  "latest": "0.1.0",
  "releases": [
    {
      "version": "0.1.0",
      "date": "2026-07-20",
      "title": "移动端首个可测试版本",
      "channel": "stable",
      "published": true,
      "releaseUrl": "https://github.com/kengqin/book/releases/tag/mobile-v0.1.0",
      "storeUrls": {
        "androidApk": "https://github.com/kengqin/book/releases/download/mobile-v0.1.0/novel-library-mobile-0.1.0.apk"
      },
      "apkSha256": "b0e83ff6abcbb28f83f83e7afb197aabf68f8f2887ebc03469975e8b5da73fb0",
      "sections": [
        {
          "title": "首版能力",
          "items": [
            "TXT/EPUB 导入",
            "本地阅读和备份恢复"
          ]
        }
      ]
    }
  ]
}
